.gitignore
LICENSE
MANIFEST.in
README.md
README.rst
setup.py
upsilon/__init__.py
upsilon.egg-info/PKG-INFO
upsilon.egg-info/SOURCES.txt
upsilon.egg-info/dependency_links.txt
upsilon.egg-info/requires.txt
upsilon.egg-info/top_level.txt
upsilon/datasets/__init__.py
upsilon/datasets/base.py
upsilon/datasets/images/.DS_Store
upsilon/datasets/images/UPSILoN.png
upsilon/datasets/images/model_map_subclass.github.png
upsilon/datasets/lightcurves/lm0010n22323.time
upsilon/datasets/models/.DS_Store
upsilon/datasets/models/rf.model.sub.github.gz
upsilon/extract_features/__init__.py
upsilon/extract_features/extract_features.py
upsilon/extract_features/feature_set.py
upsilon/extract_features/is_period_alias.py
upsilon/extract_features/period_LS_pyfftw.py
upsilon/predict/__init__.py
upsilon/predict/predict.py
upsilon/test/__init__.py
upsilon/test/extract_features.py
upsilon/test/predict.py
upsilon/utils/__init__.py
upsilon/utils/logger.py
upsilon/utils/utils.py