Metadata-Version: 1.1
Name: upsilon
Version: 1.2.3
Summary: Automated Classification of Periodic Variable Stars Using Machine Learning
Home-page: https://github.com/dwkim78/upsilon
Author: Dae-Won Kim
Author-email: dwkim78@gmail.com
License: MIT
Keywords: astronomy,periodic variables,light curves,variability features,time-series survey,machine learning,classification
Platform: any
Classifier: Development Status :: 5 - Production/Stable
Classifier: Intended Audience :: Science/Research
Classifier: License :: OSI Approved :: MIT License
Classifier: Natural Language :: English
Classifier: Operating System :: OS Independent
Classifier: Programming Language :: Python :: 2.7
Classifier: Topic :: Scientific/Engineering :: Artificial Intelligence
Classifier: Topic :: Scientific/Engineering :: Astronomy
